README.md
setup.cfg
setup.py
raimixer/__init__.py
raimixer/__main__.py
raimixer/cli.py
raimixer/config.py
raimixer/gui.py
raimixer/raimixer.py
raimixer/rairpc.py
raimixer/test.py
raimixer/utils.py
raimixer/version.py
raimixer.egg-info/PKG-INFO
raimixer.egg-info/SOURCES.txt
raimixer.egg-info/dependency_links.txt
raimixer.egg-info/entry_points.txt
raimixer.egg-info/requires.txt
raimixer.egg-info/top_level.txt