Metadata-Version: 1.1
Name: raimixer
Version: 1.2.0
Summary: Mix/scramble RaiBlocks transactions between random local accounts before sending to the real destination.
Home-page: https://github.com/juanjux/raimixer
Author: Juanjo Alvarez
Author-email: gorthol@protonmail.com
License: GPL 3.0
Download-URL: https://github.com/juanjux/raimixer/archive/v1.2.0.tar.gz
Platform: UNKNOWN
Classifier: Development Status :: 3 - Alpha
Classifier: Environment :: Console
Classifier: Intended Audience :: Information Technology
Classifier: Intended Audience :: Financial and Insurance Industry
Classifier: Topic :: Security
Classifier: Topic :: Security :: Cryptography
Classifier: Operating System :: OS Independent
Classifier: Programming Language :: Python :: 3.6
